README.rst
setup.cfg
setup.py
crepopy/__init__.py
crepopy/add_key.py
crepopy/create.py
crepopy/list_repos.py
crepopy/main.py
crepopy.egg-info/PKG-INFO
crepopy.egg-info/SOURCES.txt
crepopy.egg-info/dependency_links.txt
crepopy.egg-info/entry_points.txt
crepopy.egg-info/namespace_packages.txt
crepopy.egg-info/requires.txt
crepopy.egg-info/top_level.txt