Metadata-Version: 1.1
Name: crepopy
Version: 0.0.3a
Summary: crepopy
Home-page: https://github.com/jamesbeedy/crepopy
Author: jamesbeedy
Author-email: jamesbeedy@gmail.com
License: UNKNOWN
Download-URL: https://github.com/jamesbeedy/crepopy
Keywords: sample setuptools development
Platform: Any
Classifier: Development Status :: 3 - Alpha
Classifier: Intended Audience :: Developers
Classifier: Topic :: Software Development :: Build Tools
Classifier: License :: OSI Approved :: Apache Software License
Classifier: Programming Language :: Python
Classifier: Programming Language :: Python :: 2
Classifier: Programming Language :: Python :: 2.7
Classifier: Programming Language :: Python :: 3
Classifier: Programming Language :: Python :: 3.2
Classifier: Intended Audience :: Developers
Classifier: Environment :: Console
